angry_logger/__init__.py
angry_logger/_const.py
angry_logger/logging.py
angry_logger-1.0.1.dist-info/WHEEL
angry_logger-1.0.1.dist-info/METADATA
angry_logger-1.0.1.dist-info/RECORD
