Metadata-Version: 2.1
Name: angry-logger
Version: 1.0.1
Summary: Make your logging more passive agressive. Or just agressive agressive.
Home-page: https://github.com/GitToby/angry-logger
License: MIT
Author: Toby Devlin
Author-email: toby@tobydevlin.com
Requires-Python: >=3.7,<4.0
Classifier: License :: OSI Approved :: MIT License
Classifier: Programming Language :: Python :: 3
Classifier: Programming Language :: Python :: 3.7
Classifier: Programming Language :: Python :: 3.8
Classifier: Programming Language :: Python :: 3.9
Classifier: Programming Language :: Python :: 3.10
Classifier: Programming Language :: Python :: 3.11
Project-URL: PyPi, https://pypi.org/project/angry-logger/
